[{"kind": "element", "description": "Web Component to display stock price", "version": "v1.0.1", "updated_at": "2017-03-16T01:26:52Z", "repo": "stock-value", "avatar_url": "https://avatars3.githubusercontent.com/u/6173664?v=4", "stars": 0, "subscribers": 2, "owner": "valdrinkoshi", "forks": 0, "dependency_count": 0}, {"kind": "element", "description": "🐥 Pokémon selector. There's an element for that.", "version": "v0.0.4", "updated_at": "2017-06-27T23:20:23Z", "repo": "pokemon-selector", "avatar_url": "https://avatars1.githubusercontent.com/u/8615573?v=4", "stars": 6, "subscribers": 1, "owner": "samiheikki", "forks": 1, "dependency_count": 4}, {"kind": "element", "description": "web component tools for api weezevent", "version": "v1.2.6", "updated_at": "2017-06-19T22:41:32Z", "repo": "service-weezevent", "avatar_url": "https://avatars0.githubusercontent.com/u/8178740?v=4", "stars": 0, "subscribers": 0, "owner": "Raulnet", "forks": 0, "dependency_count": 2}, {"kind": "element", "description": "Provides a simple Webcomponent to make its Bitcoin Price Index (BPI) available to others", "version": "0.0.2", "updated_at": "2017-02-17T21:47:08Z", "repo": "coindesk-component", "avatar_url": "https://avatars0.githubusercontent.com/u/1218398?v=4", "stars": 1, "subscribers": 1, "owner": "joserochadocarmo", "forks": 0, "dependency_count": 2}, {"kind": "element", "description": "Polymer File Dropzone Element", "version": "v1.1.1", "updated_at": "2017-08-25T23:10:13Z", "repo": "file-dropzone", "avatar_url": "https://avatars0.githubusercontent.com/u/1587563?v=4", "stars": 3, "subscribers": 1, "owner": "woutervroege", "forks": 1, "dependency_count": 1}, {"kind": "element", "description": "A floating action button flinging out related actions", "version": "v0.6.0", "updated_at": "2017-07-03T18:09:35Z", "repo": "paper-fab-speed-dial", "avatar_url": "https://avatars1.githubusercontent.com/u/1911623?v=4", "stars": 12, "subscribers": 1, "owner": "pomber", "forks": 5, "dependency_count": 3}, {"kind": "element", "description": "Fork this repo if you want to start your own Web Component using Polymer", "version": "v0.1.4", "updated_at": "2017-07-28T08:50:26Z", "repo": "juicy-polymer-boilerplate", "avatar_url": "https://avatars0.githubusercontent.com/u/7557694?v=4", "stars": 0, "subscribers": 15, "owner": "Juicy", "forks": 0, "dependency_count": 1}, {"kind": "element", "description": "Polymer + Web Animations", "version": "v2.0.1", "updated_at": "2017-09-19T16:55:33Z", "repo": "neon-animation", "avatar_url": "https://avatars1.githubusercontent.com/u/11639138?v=4", "stars": 131, "subscribers": 39, "owner": "PolymerElements", "forks": 105, "dependency_count": 4}, {"kind": "element", "description": "Style mixins for cross-platform flex-box layouts", "version": "v2.0.0", "updated_at": "2017-09-26T02:37:09Z", "repo": "iron-flex-layout", "avatar_url": "https://avatars1.githubusercontent.com/u/11639138?v=4", "stars": 71, "subscribers": 24, "owner": "PolymerElements", "forks": 63, "dependency_count": 1}, {"kind": "element", "description": "A webcomponent to render a QR Code", "version": "1.1.3", "updated_at": "2017-06-19T16:11:32Z", "repo": "granite-qrcode-generator", "avatar_url": "https://avatars0.githubusercontent.com/u/726476?v=4", "stars": 8, "subscribers": 2, "owner": "LostInBrittany", "forks": 3, "dependency_count": 2}, {"kind": "element", "description": "Horizontal toolbar containing items that can be used for label, navigation, search and actions", "version": "v2.0.2", "updated_at": "2017-07-18T19:29:26Z", "repo": "ibm-toolbar", "avatar_url": "https://avatars1.githubusercontent.com/u/22341564?v=4", "stars": 13, "subscribers": 3, "owner": "IBMResearch", "forks": 3, "dependency_count": 2}, {"kind": "element", "description": "Google Spreadsheets web components ", "version": "v1.0.6", "updated_at": "2017-09-22T09:03:20Z", "repo": "google-sheets", "avatar_url": "https://avatars1.githubusercontent.com/u/7328930?v=4", "stars": 59, "subscribers": 18, "owner": "GoogleWebComponents", "forks": 22, "dependency_count": 4}, {"kind": "element", "description": "A simple pagination control with an paper-input for Polymer", "version": "v1.0.2", "updated_at": "2017-09-05T19:30:30Z", "repo": "pagination-input", "avatar_url": "https://avatars2.githubusercontent.com/u/19496563?v=4", "stars": 0, "subscribers": 1, "owner": "cforgeard", "forks": 0, "dependency_count": 5}, {"kind": "element", "description": "Web Component (with Polymer) to listen the Konami Code (↑↑↓↓←→←→BA)", "version": "v0.1.1", "updated_at": "2017-07-11T15:29:29Z", "repo": "konami-code", "avatar_url": "https://avatars1.githubusercontent.com/u/1007051?v=4", "stars": 7, "subscribers": 1, "owner": "abdonrd", "forks": 1, "dependency_count": 2}, {"kind": "element", "description": "A Material Design progress", "version": "v2.0.1", "updated_at": "2017-09-13T19:27:30Z", "repo": "paper-progress", "avatar_url": "https://avatars1.githubusercontent.com/u/11639138?v=4", "stars": 27, "subscribers": 24, "owner": "PolymerElements", "forks": 34, "dependency_count": 4}, {"kind": "element", "description": "Element for creating and accessing self-organizing meta-databases", "version": "v2.0.2", "updated_at": "2017-09-25T06:38:53Z", "repo": "iron-meta", "avatar_url": "https://avatars1.githubusercontent.com/u/11639138?v=4", "stars": 18, "subscribers": 23, "owner": "PolymerElements", "forks": 16, "dependency_count": 1}, {"kind": "element", "description": "Textarea that grows in height as more lines of input are entered", "version": "v2.1.0", "updated_at": "2017-06-14T11:59:28Z", "repo": "iron-autogrow-textarea", "avatar_url": "https://avatars1.githubusercontent.com/u/11639138?v=4", "stars": 11, "subscribers": 20, "owner": "PolymerElements", "forks": 34, "dependency_count": 4}, {"kind": "element", "description": "Expression of a vocabulary term", "version": "1.0.1", "updated_at": "2017-08-01T11:46:03Z", "repo": "lrn-vocab", "avatar_url": "https://avatars2.githubusercontent.com/u/26451082?v=4", "stars": 0, "subscribers": 2, "owner": "LRNWebComponents", "forks": 0, "dependency_count": 8}, {"kind": "element", "description": "Tabs are used to separate content into different panes", "version": "v2.0.1", "updated_at": "2017-07-18T19:29:37Z", "repo": "ibm-tabs", "avatar_url": "https://avatars1.githubusercontent.com/u/22341564?v=4", "stars": 6, "subscribers": 3, "owner": "IBMResearch", "forks": 2, "dependency_count": 4}, {"kind": "element", "description": "Social Buttons as Web Components", "version": "v0.3.0", "updated_at": "2017-09-09T04:41:53Z", "repo": "social-button", "avatar_url": "https://avatars3.githubusercontent.com/u/1800018?v=4", "stars": 14, "subscribers": 1, "owner": "1000ch", "forks": 0, "dependency_count": 0}]